<?xml version="1.0" encoding="UTF-8"?>

<!-- generated on 2024-01-28 19:49:57 by Eclipse SUMO sumo Version 1.14.1
<configuration xmlns:xsi="http://www.w3.org/2001/XMLSchema-instance" xsi:noNamespaceSchemaLocation="http://sumo.dlr.de/xsd/sumoConfiguration.xsd">

    <input>
        <net-file value=".\singapore.net.xml"/>
        <route-files value="trips.trips.xml"/>
        <additional-files value=".\busstops.xml"/>
    </input>

    <output>
        <vehroute-output value="vehroutes.xml"/>
        <stop-output value="stopinfos.xml"/>
    </output>

    <time>
        <begin value="0"/>
    </time>

    <processing>
        <ignore-route-errors value="true"/>
    </processing>

    <routing>
        <device.rerouting.adaptation-interval value="0"/>
    </routing>

    <report>
        <aggregate-warnings value="5"/>
        <error-log value="trips.trips.xml.errorlog"/>
        <no-step-log value="true"/>
    </report>

</configuration>
-->

<stops xmlns:xsi="http://www.w3.org/2001/XMLSchema-instance" xsi:noNamespaceSchemaLocation="http://sumo.dlr.de/xsd/stopinfo_file.xsd">
    <stopinfo id="0_bus_22:0" type="bus" lane="543768663_0" pos="7.80" parking="0" started="1.00" ended="31.00" delay="-1.00" initialPersons="0" loadedPersons="0" unloadedPersons="0" initialContainers="0" loadedContainers="0" unloadedContainers="0" busStop="410460005"/>
    <stopinfo id="1_bus_43:0" type="bus" lane="74962088_0" pos="57.23" parking="0" started="32.00" ended="62.00" delay="-1.00" initialPersons="0" loadedPersons="0" unloadedPersons="0" initialContainers="0" loadedContainers="0" unloadedContainers="0" busStop="1847853709"/>
    <stopinfo id="1_bus_43:0" type="bus" lane="74962088_0" pos="57.95" parking="0" started="63.00" ended="93.00" delay="-1.00" initialPersons="0" loadedPersons="0" unloadedPersons="0" initialContainers="0" loadedContainers="0" unloadedContainers="0" busStop="7314770844"/>
    <stopinfo id="0_bus_22:0" type="bus" lane="630171311_0" pos="11.35" parking="0" started="117.00" ended="147.00" delay="-1.00" initialPersons="0" loadedPersons="0" unloadedPersons="0" initialContainers="0" loadedContainers="0" unloadedContainers="0" busStop="410459901"/>
    <stopinfo id="1_bus_43:0" type="bus" lane="582412262_0" pos="37.02" parking="0" started="126.00" ended="156.00" delay="-1.00" initialPersons="0" loadedPersons="0" unloadedPersons="0" initialContainers="0" loadedContainers="0" unloadedContainers="0" busStop="3865151058"/>
    <stopinfo id="1_bus_43:0" type="bus" lane="717446182_0" pos="58.45" parking="0" started="193.00" ended="223.00" delay="-1.00" initialPersons="0" loadedPersons="0" unloadedPersons="0" initialContainers="0" loadedContainers="0" unloadedContainers="0" busStop="1849631331"/>
    <stopinfo id="0_bus_22:0" type="bus" lane="482256070_0" pos="39.15" parking="0" started="196.00" ended="226.00" delay="-1.00" initialPersons="0" loadedPersons="0" unloadedPersons="0" initialContainers="0" loadedContainers="0" unloadedContainers="0" busStop="410459897"/>
    <stopinfo id="0_bus_22:0" type="bus" lane="652293278_0" pos="35.19" parking="0" started="243.00" ended="273.00" delay="-1.00" initialPersons="0" loadedPersons="0" unloadedPersons="0" initialContainers="0" loadedContainers="0" unloadedContainers="0" busStop="410459904"/>
    <stopinfo id="1_bus_43:0" type="bus" lane="190451325_0" pos="73.90" parking="0" started="259.00" ended="289.00" delay="-1.00" initialPersons="0" loadedPersons="0" unloadedPersons="0" initialContainers="0" loadedContainers="0" unloadedContainers="0" busStop="3737148763"/>
    <stopinfo id="0_bus_22:0" type="bus" lane="634469471_0" pos="53.70" parking="0" started="312.00" ended="342.00" delay="-1.00" initialPersons="0" loadedPersons="0" unloadedPersons="0" initialContainers="0" loadedContainers="0" unloadedContainers="0" busStop="410459657"/>
    <stopinfo id="1_bus_43:0" type="bus" lane="349416402_0" pos="140.87" parking="0" started="334.00" ended="364.00" delay="-1.00" initialPersons="0" loadedPersons="0" unloadedPersons="0" initialContainers="0" loadedContainers="0" unloadedContainers="0" busStop="8926967788"/>
    <stopinfo id="0_bus_22:0" type="bus" lane="630160531_0" pos="31.18" parking="0" started="396.00" ended="426.00" delay="-1.00" initialPersons="0" loadedPersons="0" unloadedPersons="0" initialContainers="0" loadedContainers="0" unloadedContainers="0" busStop="410459651"/>
    <stopinfo id="1_bus_43:0" type="bus" lane="717470516_0" pos="47.21" parking="0" started="397.00" ended="427.00" delay="-1.00" initialPersons="0" loadedPersons="0" unloadedPersons="0" initialContainers="0" loadedContainers="0" unloadedContainers="0" busStop="410474760"/>
    <stopinfo id="1_bus_43:0" type="bus" lane="445716748_0" pos="41.59" parking="0" started="452.00" ended="482.00" delay="-1.00" initialPersons="0" loadedPersons="0" unloadedPersons="0" initialContainers="0" loadedContainers="0" unloadedContainers="0" busStop="410474348"/>
    <stopinfo id="0_bus_22:0" type="bus" lane="630163199_0" pos="23.99" parking="0" started="484.00" ended="514.00" delay="-1.00" initialPersons="0" loadedPersons="0" unloadedPersons="0" initialContainers="0" loadedContainers="0" unloadedContainers="0" busStop="410467153"/>
    <stopinfo id="1_bus_43:0" type="bus" lane="22652564_0" pos="10.28" parking="0" started="539.00" ended="569.00" delay="-1.00" initialPersons="0" loadedPersons="0" unloadedPersons="0" initialContainers="0" loadedContainers="0" unloadedContainers="0" busStop="1849631269"/>
    <stopinfo id="0_bus_22:0" type="bus" lane="661628136_0" pos="27.45" parking="0" started="558.00" ended="588.00" delay="-1.00" initialPersons="0" loadedPersons="0" unloadedPersons="0" initialContainers="0" loadedContainers="0" unloadedContainers="0" busStop="410462101"/>
    <stopinfo id="0_bus_22:0" type="bus" lane="661628136_0" pos="28.14" parking="0" started="589.00" ended="619.00" delay="-1.00" initialPersons="0" loadedPersons="0" unloadedPersons="0" initialContainers="0" loadedContainers="0" unloadedContainers="0" busStop="410462103"/>
    <stopinfo id="1_bus_43:0" type="bus" lane="623715810#0_0" pos="7.70" parking="0" started="598.00" ended="628.00" delay="-1.00" initialPersons="0" loadedPersons="0" unloadedPersons="0" initialContainers="0" loadedContainers="0" unloadedContainers="0" busStop="2429952037"/>
    <stopinfo id="1_bus_43:0" type="bus" lane="632378379#0_0" pos="11.66" parking="0" started="698.00" ended="728.00" delay="-1.00" initialPersons="0" loadedPersons="0" unloadedPersons="0" initialContainers="0" loadedContainers="0" unloadedContainers="0" busStop="1849631273"/>
    <stopinfo id="0_bus_22:0" type="bus" lane="632203646_0" pos="100.97" parking="0" started="711.00" ended="741.00" delay="-1.00" initialPersons="0" loadedPersons="0" unloadedPersons="0" initialContainers="0" loadedContainers="0" unloadedContainers="0" busStop="410475114"/>
    <stopinfo id="0_bus_22:0" type="bus" lane="479079789_0" pos="36.64" parking="0" started="773.00" ended="803.00" delay="-1.00" initialPersons="0" loadedPersons="0" unloadedPersons="0" initialContainers="0" loadedContainers="0" unloadedContainers="0" busStop="1531005322"/>
    <stopinfo id="1_bus_43:0" type="bus" lane="445716683_0" pos="66.16" parking="0" started="779.00" ended="809.00" delay="-1.00" initialPersons="0" loadedPersons="0" unloadedPersons="0" initialContainers="0" loadedContainers="0" unloadedContainers="0" busStop="410462266"/>
    <stopinfo id="1_bus_43:0" type="bus" lane="476703994_0" pos="26.43" parking="0" started="827.00" ended="857.00" delay="-1.00" initialPersons="0" loadedPersons="0" unloadedPersons="0" initialContainers="0" loadedContainers="0" unloadedContainers="0" busStop="410462293"/>
    <stopinfo id="0_bus_22:0" type="bus" lane="22293549_0" pos="181.35" parking="0" started="837.00" ended="867.00" delay="-1.00" initialPersons="0" loadedPersons="0" unloadedPersons="0" initialContainers="0" loadedContainers="0" unloadedContainers="0" busStop="410483103"/>
    <stopinfo id="1_bus_43:0" type="bus" lane="512918179_0" pos="34.61" parking="0" started="895.00" ended="925.00" delay="-1.00" initialPersons="0" loadedPersons="0" unloadedPersons="0" initialContainers="0" loadedContainers="0" unloadedContainers="0" busStop="410462211"/>
    <stopinfo id="0_bus_22:0" type="bus" lane="33264691#0_0" pos="18.85" parking="0" started="896.00" ended="926.00" delay="-1.00" initialPersons="0" loadedPersons="0" unloadedPersons="0" initialContainers="0" loadedContainers="0" unloadedContainers="0" busStop="410482520"/>
    <stopinfo id="1_bus_43:0" type="bus" lane="512918201#0_0" pos="11.16" parking="0" started="956.00" ended="986.00" delay="-1.00" initialPersons="0" loadedPersons="0" unloadedPersons="0" initialContainers="0" loadedContainers="0" unloadedContainers="0" busStop="410462291"/>
    <stopinfo id="0_bus_22:0" type="bus" lane="633299924_0" pos="36.76" parking="0" started="973.00" ended="1003.00" delay="-1.00" initialPersons="0" loadedPersons="0" unloadedPersons="0" initialContainers="0" loadedContainers="0" unloadedContainers="0" busStop="410482572"/>
    <stopinfo id="0_bus_22:0" type="bus" lane="474929430_0" pos="19.15" parking="0" started="1026.00" ended="1056.00" delay="-1.00" initialPersons="0" loadedPersons="0" unloadedPersons="0" initialContainers="0" loadedContainers="0" unloadedContainers="0" busStop="410482568"/>
    <stopinfo id="1_bus_43:0" type="bus" lane="74668469_0" pos="210.33" parking="0" started="1046.00" ended="1076.00" delay="-1.00" initialPersons="0" loadedPersons="0" unloadedPersons="0" initialContainers="0" loadedContainers="0" unloadedContainers="0" busStop="410486991"/>
    <stopinfo id="0_bus_22:0" type="bus" lane="631844130_0" pos="88.09" parking="0" started="1098.00" ended="1128.00" delay="-1.00" initialPersons="0" loadedPersons="0" unloadedPersons="0" initialContainers="0" loadedContainers="0" unloadedContainers="0" busStop="410482491"/>
    <stopinfo id="1_bus_43:0" type="bus" lane="74869296_0" pos="65.88" parking="0" started="1117.00" ended="1147.00" delay="-1.00" initialPersons="0" loadedPersons="0" unloadedPersons="0" initialContainers="0" loadedContainers="0" unloadedContainers="0" busStop="410486955"/>
    <stopinfo id="0_bus_22:0" type="bus" lane="631844130_0" pos="164.78" parking="0" started="1142.00" ended="1172.00" delay="-1.00" initialPersons="0" loadedPersons="0" unloadedPersons="0" initialContainers="0" loadedContainers="0" unloadedContainers="0" busStop="410482562"/>
    <stopinfo id="1_bus_43:0" type="bus" lane="34905413_0" pos="34.61" parking="0" started="1183.00" ended="1213.00" delay="-1.00" initialPersons="0" loadedPersons="0" unloadedPersons="0" initialContainers="0" loadedContainers="0" unloadedContainers="0" busStop="4430976208"/>
    <stopinfo id="0_bus_22:0" type="bus" lane="500368905_0" pos="103.68" parking="0" started="1223.00" ended="1253.00" delay="-1.00" initialPersons="0" loadedPersons="0" unloadedPersons="0" initialContainers="0" loadedContainers="0" unloadedContainers="0" busStop="410482564"/>
    <stopinfo id="1_bus_43:0" type="bus" lane="633197069_0" pos="16.12" parking="0" started="1242.00" ended="1272.00" delay="-1.00" initialPersons="0" loadedPersons="0" unloadedPersons="0" initialContainers="0" loadedContainers="0" unloadedContainers="0" busStop="410486969"/>
    <stopinfo id="0_bus_22:0" type="bus" lane="661665982_0" pos="107.56" parking="0" started="1282.00" ended="1312.00" delay="-1.00" initialPersons="0" loadedPersons="0" unloadedPersons="0" initialContainers="0" loadedContainers="0" unloadedContainers="0" busStop="410482570"/>
    <stopinfo id="1_bus_43:0" type="bus" lane="175959568_0" pos="45.56" parking="0" started="1314.00" ended="1344.00" delay="-1.00" initialPersons="0" loadedPersons="0" unloadedPersons="0" initialContainers="0" loadedContainers="0" unloadedContainers="0" busStop="1855320978"/>
    <stopinfo id="0_bus_22:0" type="bus" lane="661665982_0" pos="263.30" parking="0" started="1333.00" ended="1363.00" delay="-1.00" initialPersons="0" loadedPersons="0" unloadedPersons="0" initialContainers="0" loadedContainers="0" unloadedContainers="0" busStop="410482551"/>
    <stopinfo id="1_bus_43:0" type="bus" lane="630829769_0" pos="73.30" parking="0" started="1369.00" ended="1399.00" delay="-1.00" initialPersons="0" loadedPersons="0" unloadedPersons="0" initialContainers="0" loadedContainers="0" unloadedContainers="0" busStop="410486966"/>
    <stopinfo id="0_bus_22:0" type="bus" lane="630419696#0_0" pos="12.12" parking="0" started="1397.00" ended="1427.00" delay="-1.00" initialPersons="0" loadedPersons="0" unloadedPersons="0" initialContainers="0" loadedContainers="0" unloadedContainers="0" busStop="410471081"/>
    <stopinfo id="1_bus_43:0" type="bus" lane="630829769_0" pos="74.22" parking="0" started="1400.00" ended="1430.00" delay="-1.00" initialPersons="0" loadedPersons="0" unloadedPersons="0" initialContainers="0" loadedContainers="0" unloadedContainers="0" busStop="410486516"/>
    <stopinfo id="0_bus_22:0" type="bus" lane="639549066_0" pos="34.17" parking="0" started="1463.00" ended="1493.00" delay="-1.00" initialPersons="0" loadedPersons="0" unloadedPersons="0" initialContainers="0" loadedContainers="0" unloadedContainers="0" busStop="410471030"/>
    <stopinfo id="1_bus_43:0" type="bus" lane="475163615_0" pos="31.77" parking="0" started="1476.00" ended="1506.00" delay="-1.00" initialPersons="0" loadedPersons="0" unloadedPersons="0" initialContainers="0" loadedContainers="0" unloadedContainers="0" busStop="410486293"/>
    <stopinfo id="0_bus_22:0" type="bus" lane="639916002_0" pos="25.97" parking="0" started="1551.00" ended="1581.00" delay="-1.00" initialPersons="0" loadedPersons="0" unloadedPersons="0" initialContainers="0" loadedContainers="0" unloadedContainers="0" busStop="410480716"/>
    <stopinfo id="1_bus_43:0" type="bus" lane="632203646_0" pos="100.98" parking="0" started="1556.00" ended="1586.00" delay="-1.00" initialPersons="0" loadedPersons="0" unloadedPersons="0" initialContainers="0" loadedContainers="0" unloadedContainers="0" busStop="410475114"/>
    <stopinfo id="0_bus_22:0" type="bus" lane="74746296_0" pos="200.20" parking="0" started="1614.00" ended="1644.00" delay="-1.00" initialPersons="0" loadedPersons="0" unloadedPersons="0" initialContainers="0" loadedContainers="0" unloadedContainers="0" busStop="410480722"/>
    <stopinfo id="1_bus_43:0" type="bus" lane="479079789_0" pos="36.62" parking="0" started="1618.00" ended="1648.00" delay="-1.00" initialPersons="0" loadedPersons="0" unloadedPersons="0" initialContainers="0" loadedContainers="0" unloadedContainers="0" busStop="1531005322"/>
    <stopinfo id="0_bus_22:0" type="bus" lane="74746296_0" pos="328.24" parking="0" started="1664.00" ended="1694.00" delay="-1.00" initialPersons="0" loadedPersons="0" unloadedPersons="0" initialContainers="0" loadedContainers="0" unloadedContainers="0" busStop="410480721"/>
    <stopinfo id="1_bus_43:0" type="bus" lane="22293549_0" pos="181.35" parking="0" started="1680.00" ended="1710.00" delay="-1.00" initialPersons="0" loadedPersons="0" unloadedPersons="0" initialContainers="0" loadedContainers="0" unloadedContainers="0" busStop="410483103"/>
    <stopinfo id="0_bus_22:0" type="bus" lane="477574135_0" pos="141.90" parking="0" started="1733.00" ended="1763.00" delay="-1.00" initialPersons="0" loadedPersons="0" unloadedPersons="0" initialContainers="0" loadedContainers="0" unloadedContainers="0" busStop="5701793241"/>
    <stopinfo id="1_bus_43:0" type="bus" lane="33264691#0_0" pos="18.85" parking="0" started="1737.00" ended="1767.00" delay="-1.00" initialPersons="0" loadedPersons="0" unloadedPersons="0" initialContainers="0" loadedContainers="0" unloadedContainers="0" busStop="410482520"/>
    <stopinfo id="0_bus_22:0" type="bus" lane="636737164_0" pos="42.16" parking="0" started="1783.00" ended="1813.00" delay="-1.00" initialPersons="0" loadedPersons="0" unloadedPersons="0" initialContainers="0" loadedContainers="0" unloadedContainers="0" busStop="410480724"/>
    <stopinfo id="1_bus_43:0" type="bus" lane="633299924_0" pos="36.76" parking="0" started="1815.00" ended="1845.00" delay="-1.00" initialPersons="0" loadedPersons="0" unloadedPersons="0" initialContainers="0" loadedContainers="0" unloadedContainers="0" busStop="410482572"/>
    <stopinfo id="0_bus_22:0" type="bus" lane="447712957_0" pos="39.64" parking="0" started="1848.00" ended="1878.00" delay="-1.00" initialPersons="0" loadedPersons="0" unloadedPersons="0" initialContainers="0" loadedContainers="0" unloadedContainers="0" busStop="410464248"/>
    <stopinfo id="1_bus_43:0" type="bus" lane="474929430_0" pos="19.17" parking="0" started="1868.00" ended="1898.00" delay="-1.00" initialPersons="0" loadedPersons="0" unloadedPersons="0" initialContainers="0" loadedContainers="0" unloadedContainers="0" busStop="410482568"/>
    <stopinfo id="0_bus_22:0" type="bus" lane="587048092_0" pos="44.40" parking="0" started="1916.00" ended="1946.00" delay="-1.00" initialPersons="0" loadedPersons="0" unloadedPersons="0" initialContainers="0" loadedContainers="0" unloadedContainers="0" busStop="410465916"/>
    <stopinfo id="1_bus_43:0" type="bus" lane="631844130_0" pos="88.10" parking="0" started="1939.00" ended="1969.00" delay="-1.00" initialPersons="0" loadedPersons="0" unloadedPersons="0" initialContainers="0" loadedContainers="0" unloadedContainers="0" busStop="410482491"/>
    <stopinfo id="0_bus_22:0" type="bus" lane="74553776_0" pos="37.70" parking="0" started="1982.00" ended="2012.00" delay="-1.00" initialPersons="0" loadedPersons="0" unloadedPersons="0" initialContainers="0" loadedContainers="0" unloadedContainers="0" busStop="410465917"/>
    <stopinfo id="1_bus_43:0" type="bus" lane="631844130_0" pos="164.76" parking="0" started="1984.00" ended="2014.00" delay="-1.00" initialPersons="0" loadedPersons="0" unloadedPersons="0" initialContainers="0" loadedContainers="0" unloadedContainers="0" busStop="410482562"/>
    <stopinfo id="0_bus_22:0" type="bus" lane="473440854_0" pos="11.72" parking="0" started="2056.00" ended="2086.00" delay="-1.00" initialPersons="0" loadedPersons="0" unloadedPersons="0" initialContainers="0" loadedContainers="0" unloadedContainers="0" busStop="410465915"/>
    <stopinfo id="1_bus_43:0" type="bus" lane="500368905_0" pos="103.66" parking="0" started="2064.00" ended="2094.00" delay="-1.00" initialPersons="0" loadedPersons="0" unloadedPersons="0" initialContainers="0" loadedContainers="0" unloadedContainers="0" busStop="410482564"/>
    <stopinfo id="1_bus_43:0" type="bus" lane="661665982_0" pos="107.56" parking="0" started="2124.00" ended="2154.00" delay="-1.00" initialPersons="0" loadedPersons="0" unloadedPersons="0" initialContainers="0" loadedContainers="0" unloadedContainers="0" busStop="410482570"/>
    <stopinfo id="0_bus_22:0" type="bus" lane="585646221#0_0" pos="12.27" parking="0" started="2129.00" ended="2159.00" delay="-1.00" initialPersons="0" loadedPersons="0" unloadedPersons="0" initialContainers="0" loadedContainers="0" unloadedContainers="0" busStop="410462762"/>
    <stopinfo id="1_bus_43:0" type="bus" lane="661665982_0" pos="263.28" parking="0" started="2175.00" ended="2205.00" delay="-1.00" initialPersons="0" loadedPersons="0" unloadedPersons="0" initialContainers="0" loadedContainers="0" unloadedContainers="0" busStop="410482551"/>
    <stopinfo id="0_bus_22:0" type="bus" lane="23816952_0" pos="85.49" parking="0" started="2229.00" ended="2259.00" delay="-1.00" initialPersons="0" loadedPersons="0" unloadedPersons="0" initialContainers="0" loadedContainers="0" unloadedContainers="0" busStop="410466111"/>
    <stopinfo id="1_bus_43:0" type="bus" lane="630419696#0_0" pos="12.11" parking="0" started="2238.00" ended="2268.00" delay="-1.00" initialPersons="0" loadedPersons="0" unloadedPersons="0" initialContainers="0" loadedContainers="0" unloadedContainers="0" busStop="410471081"/>
    <stopinfo id="1_bus_43:0" type="bus" lane="639549066_0" pos="34.17" parking="0" started="2306.00" ended="2336.00" delay="-1.00" initialPersons="0" loadedPersons="0" unloadedPersons="0" initialContainers="0" loadedContainers="0" unloadedContainers="0" busStop="410471030"/>
    <stopinfo id="0_bus_22:0" type="bus" lane="245934570#2_0" pos="272.82" parking="0" started="2362.00" ended="2392.00" delay="-1.00" initialPersons="0" loadedPersons="0" unloadedPersons="0" initialContainers="0" loadedContainers="0" unloadedContainers="0" busStop="410464251"/>
    <stopinfo id="1_bus_43:0" type="bus" lane="587050477#0_0" pos="7.70" parking="0" started="2439.00" ended="2469.00" delay="-1.00" initialPersons="0" loadedPersons="0" unloadedPersons="0" initialContainers="0" loadedContainers="0" unloadedContainers="0" busStop="410470959"/>
    <stopinfo id="1_bus_43:0" type="bus" lane="585706001_0" pos="93.53" parking="0" started="2513.00" ended="2543.00" delay="-1.00" initialPersons="0" loadedPersons="0" unloadedPersons="0" initialContainers="0" loadedContainers="0" unloadedContainers="0" busStop="410471005"/>
    <stopinfo id="1_bus_43:0" type="bus" lane="585646209#0_0" pos="9.26" parking="0" started="2570.00" ended="2600.00" delay="-1.00" initialPersons="0" loadedPersons="0" unloadedPersons="0" initialContainers="0" loadedContainers="0" unloadedContainers="0" busStop="410464255"/>
    <stopinfo id="1_bus_43:0" type="bus" lane="652012496_0" pos="45.44" parking="0" started="2655.00" ended="2685.00" delay="-1.00" initialPersons="0" loadedPersons="0" unloadedPersons="0" initialContainers="0" loadedContainers="0" unloadedContainers="0" busStop="410478275"/>
    <stopinfo id="1_bus_43:0" type="bus" lane="-22810638_0" pos="26.15" parking="0" started="2723.00" ended="2753.00" delay="-1.00" initialPersons="0" loadedPersons="0" unloadedPersons="0" initialContainers="0" loadedContainers="0" unloadedContainers="0" busStop="-410478274"/>
    <stopinfo id="1_bus_43:0" type="bus" lane="-22810638_0" pos="72.28" parking="0" started="2764.00" ended="2794.00" delay="-1.00" initialPersons="0" loadedPersons="0" unloadedPersons="0" initialContainers="0" loadedContainers="0" unloadedContainers="0" busStop="-410478273"/>
    <stopinfo id="1_bus_43:0" type="bus" lane="-747299409_0" pos="24.48" parking="0" started="2842.00" ended="2872.00" delay="-1.00" initialPersons="0" loadedPersons="0" unloadedPersons="0" initialContainers="0" loadedContainers="0" unloadedContainers="0" busStop="-1849457018"/>
    <stopinfo id="1_bus_43:0" type="bus" lane="536913703_0" pos="7.70" parking="0" started="2915.00" ended="2945.00" delay="-1.00" initialPersons="0" loadedPersons="0" unloadedPersons="0" initialContainers="0" loadedContainers="0" unloadedContainers="0" busStop="410478271"/>
    <stopinfo id="1_bus_43:0" type="bus" lane="535665920_0" pos="13.94" parking="0" started="3020.00" ended="3050.00" delay="-1.00" initialPersons="0" loadedPersons="0" unloadedPersons="0" initialContainers="0" loadedContainers="0" unloadedContainers="0" busStop="410459494"/>
    <stopinfo id="1_bus_43:0" type="bus" lane="467731257#0_0" pos="64.55" parking="0" started="3117.00" ended="3147.00" delay="-1.00" initialPersons="0" loadedPersons="0" unloadedPersons="0" initialContainers="0" loadedContainers="0" unloadedContainers="0" busStop="4623289717"/>
    <stopinfo id="1_bus_43:0" type="bus" lane="474427034_0" pos="81.85" parking="0" started="3182.00" ended="3212.00" delay="-1.00" initialPersons="0" loadedPersons="0" unloadedPersons="0" initialContainers="0" loadedContainers="0" unloadedContainers="0" busStop="410467553"/>
    <stopinfo id="1_bus_43:0" type="bus" lane="22698751#0_0" pos="12.88" parking="0" started="3240.00" ended="3270.00" delay="-1.00" initialPersons="0" loadedPersons="0" unloadedPersons="0" initialContainers="0" loadedContainers="0" unloadedContainers="0" busStop="410467566"/>
    <stopinfo id="1_bus_43:0" type="bus" lane="74518787_0" pos="69.90" parking="0" started="3310.00" ended="3340.00" delay="-1.00" initialPersons="0" loadedPersons="0" unloadedPersons="0" initialContainers="0" loadedContainers="0" unloadedContainers="0" busStop="410467564"/>
    <stopinfo id="1_bus_43:0" type="bus" lane="74518787_0" pos="70.59" parking="0" started="3341.00" ended="3371.00" delay="-1.00" initialPersons="0" loadedPersons="0" unloadedPersons="0" initialContainers="0" loadedContainers="0" unloadedContainers="0" busStop="1268343846"/>
    <stopinfo id="1_bus_43:0" type="bus" lane="474210631_0" pos="136.23" parking="0" started="3437.00" ended="3467.00" delay="-1.00" initialPersons="0" loadedPersons="0" unloadedPersons="0" initialContainers="0" loadedContainers="0" unloadedContainers="0" busStop="410467574"/>
    <stopinfo id="1_bus_43:0" type="bus" lane="474210631_0" pos="459.58" parking="0" started="3500.00" ended="3530.00" delay="-1.00" initialPersons="0" loadedPersons="0" unloadedPersons="0" initialContainers="0" loadedContainers="0" unloadedContainers="0" busStop="410467562"/>
    <stopinfo id="1_bus_43:0" type="bus" lane="474431399_0" pos="117.10" parking="0" started="3564.00" ended="3594.00" delay="-1.00" initialPersons="0" loadedPersons="0" unloadedPersons="0" initialContainers="0" loadedContainers="0" unloadedContainers="0" busStop="410467567"/>
    <stopinfo id="1_bus_43:0" type="bus" lane="474446538_0" pos="55.79" parking="0" started="3651.00" ended="3681.00" delay="-1.00" initialPersons="0" loadedPersons="0" unloadedPersons="0" initialContainers="0" loadedContainers="0" unloadedContainers="0" busStop="410467571"/>
    <stopinfo id="1_bus_43:0" type="bus" lane="474446538_0" pos="62.15" parking="0" started="3687.00" ended="3717.00" delay="-1.00" initialPersons="0" loadedPersons="0" unloadedPersons="0" initialContainers="0" loadedContainers="0" unloadedContainers="0" busStop="410461658"/>
    <stopinfo id="1_bus_43:0" type="bus" lane="585984926_0" pos="32.35" parking="0" started="3757.00" ended="3787.00" delay="-1.00" initialPersons="0" loadedPersons="0" unloadedPersons="0" initialContainers="0" loadedContainers="0" unloadedContainers="0" busStop="410481810"/>
    <stopinfo id="1_bus_43:0" type="bus" lane="585984926_0" pos="32.99" parking="0" started="3788.00" ended="3818.00" delay="-1.00" initialPersons="0" loadedPersons="0" unloadedPersons="0" initialContainers="0" loadedContainers="0" unloadedContainers="0" busStop="410481815"/>
    <stopinfo id="1_bus_43:0" type="bus" lane="585984926_0" pos="34.13" parking="0" started="3819.00" ended="3849.00" delay="-1.00" initialPersons="0" loadedPersons="0" unloadedPersons="0" initialContainers="0" loadedContainers="0" unloadedContainers="0" busStop="410481781"/>
    <stopinfo id="1_bus_43:0" type="bus" lane="585984926_0" pos="35.31" parking="0" started="3850.00" ended="3880.00" delay="-1.00" initialPersons="0" loadedPersons="0" unloadedPersons="0" initialContainers="0" loadedContainers="0" unloadedContainers="0" busStop="410481783"/>
    <stopinfo id="1_bus_43:0" type="bus" lane="585984913_0" pos="45.25" parking="0" started="3993.00" ended="4023.00" delay="-1.00" initialPersons="0" loadedPersons="0" unloadedPersons="0" initialContainers="0" loadedContainers="0" unloadedContainers="0" busStop="410482047"/>
    <stopinfo id="1_bus_43:0" type="bus" lane="769243289_0" pos="26.08" parking="0" started="4084.00" ended="4114.00" delay="-1.00" initialPersons="0" loadedPersons="0" unloadedPersons="0" initialContainers="0" loadedContainers="0" unloadedContainers="0" busStop="410482019"/>
    <stopinfo id="1_bus_43:0" type="bus" lane="528461109_0" pos="16.47" parking="0" started="4154.00" ended="4184.00" delay="-1.00" initialPersons="0" loadedPersons="0" unloadedPersons="0" initialContainers="0" loadedContainers="0" unloadedContainers="0" busStop="1847713996"/>
</stops>
