<?xml version="1.0" encoding="UTF-8"?>

<!-- generated on 2024-01-25 21:57:05 by Eclipse SUMO sumo Version 1.14.1
<configuration xmlns:xsi="http://www.w3.org/2001/XMLSchema-instance" xsi:noNamespaceSchemaLocation="http://sumo.dlr.de/xsd/sumoConfiguration.xsd">

    <input>
        <net-file value=".\singapore.net.xml"/>
        <route-files value="trips.trips.xml"/>
        <additional-files value=".\busstops.xml"/>
    </input>

    <output>
        <vehroute-output value="vehroutes.xml"/>
        <stop-output value="stopinfos.xml"/>
    </output>

    <time>
        <begin value="0"/>
    </time>

    <processing>
        <ignore-route-errors value="true"/>
    </processing>

    <routing>
        <device.rerouting.adaptation-interval value="0"/>
    </routing>

    <report>
        <aggregate-warnings value="5"/>
        <error-log value="trips.trips.xml.errorlog"/>
        <no-step-log value="true"/>
    </report>

</configuration>
-->

<stops xmlns:xsi="http://www.w3.org/2001/XMLSchema-instance" xsi:noNamespaceSchemaLocation="http://sumo.dlr.de/xsd/stopinfo_file.xsd">
    <stopinfo id="3_bus_43:1" type="bus" lane="528461109_0" pos="9.15" parking="0" started="1.00" ended="31.00" delay="-1.00" initialPersons="0" loadedPersons="0" unloadedPersons="0" initialContainers="0" loadedContainers="0" unloadedContainers="0" busStop="1847713996@6623041"/>
    <stopinfo id="0_bus_22:0" type="bus" lane="543768663_0" pos="7.80" parking="0" started="1.00" ended="31.00" delay="-1.00" initialPersons="0" loadedPersons="0" unloadedPersons="0" initialContainers="0" loadedContainers="0" unloadedContainers="0" busStop="410460005"/>
    <stopinfo id="1_bus_43:0" type="bus" lane="74962088_0" pos="57.23" parking="0" started="32.00" ended="62.00" delay="-1.00" initialPersons="0" loadedPersons="0" unloadedPersons="0" initialContainers="0" loadedContainers="0" unloadedContainers="0" busStop="1847853709"/>
    <stopinfo id="1_bus_43:0" type="bus" lane="74962088_0" pos="57.95" parking="0" started="63.00" ended="93.00" delay="-1.00" initialPersons="0" loadedPersons="0" unloadedPersons="0" initialContainers="0" loadedContainers="0" unloadedContainers="0" busStop="7314770844"/>
    <stopinfo id="3_bus_43:1" type="bus" lane="639626489_0" pos="39.72" parking="0" started="103.00" ended="133.00" delay="-1.00" initialPersons="0" loadedPersons="0" unloadedPersons="0" initialContainers="0" loadedContainers="0" unloadedContainers="0" busStop="410481823"/>
    <stopinfo id="0_bus_22:0" type="bus" lane="630171311_0" pos="11.35" parking="0" started="117.00" ended="147.00" delay="-1.00" initialPersons="0" loadedPersons="0" unloadedPersons="0" initialContainers="0" loadedContainers="0" unloadedContainers="0" busStop="410459901"/>
    <stopinfo id="1_bus_43:0" type="bus" lane="582412262_0" pos="37.01" parking="0" started="126.00" ended="156.00" delay="-1.00" initialPersons="0" loadedPersons="0" unloadedPersons="0" initialContainers="0" loadedContainers="0" unloadedContainers="0" busStop="3865151058"/>
    <stopinfo id="3_bus_43:1" type="bus" lane="464205497_0" pos="31.07" parking="0" started="169.00" ended="199.00" delay="-1.00" initialPersons="0" loadedPersons="0" unloadedPersons="0" initialContainers="0" loadedContainers="0" unloadedContainers="0" busStop="410481904"/>
    <stopinfo id="1_bus_43:0" type="bus" lane="717446182_0" pos="58.45" parking="0" started="192.00" ended="222.00" delay="-1.00" initialPersons="0" loadedPersons="0" unloadedPersons="0" initialContainers="0" loadedContainers="0" unloadedContainers="0" busStop="1849631331"/>
    <stopinfo id="0_bus_22:0" type="bus" lane="482256070_0" pos="39.16" parking="0" started="196.00" ended="226.00" delay="-1.00" initialPersons="0" loadedPersons="0" unloadedPersons="0" initialContainers="0" loadedContainers="0" unloadedContainers="0" busStop="410459897"/>
    <stopinfo id="3_bus_43:1" type="bus" lane="445716787_0" pos="36.23" parking="0" started="237.00" ended="267.00" delay="-1.00" initialPersons="0" loadedPersons="0" unloadedPersons="0" initialContainers="0" loadedContainers="0" unloadedContainers="0" busStop="410481816"/>
    <stopinfo id="0_bus_22:0" type="bus" lane="652293278_0" pos="35.21" parking="0" started="242.00" ended="272.00" delay="-1.00" initialPersons="0" loadedPersons="0" unloadedPersons="0" initialContainers="0" loadedContainers="0" unloadedContainers="0" busStop="410459904"/>
    <stopinfo id="1_bus_43:0" type="bus" lane="190451325_0" pos="73.90" parking="0" started="258.00" ended="288.00" delay="-1.00" initialPersons="0" loadedPersons="0" unloadedPersons="0" initialContainers="0" loadedContainers="0" unloadedContainers="0" busStop="3737148763"/>
    <stopinfo id="3_bus_43:1" type="bus" lane="445716787_0" pos="37.40" parking="0" started="268.00" ended="298.00" delay="-1.00" initialPersons="0" loadedPersons="0" unloadedPersons="0" initialContainers="0" loadedContainers="0" unloadedContainers="0" busStop="410481787"/>
    <stopinfo id="3_bus_43:1" type="bus" lane="445716787_0" pos="38.30" parking="0" started="299.00" ended="329.00" delay="-1.00" initialPersons="0" loadedPersons="0" unloadedPersons="0" initialContainers="0" loadedContainers="0" unloadedContainers="0" busStop="410481813"/>
    <stopinfo id="0_bus_22:0" type="bus" lane="634469471_0" pos="53.69" parking="0" started="311.00" ended="341.00" delay="-1.00" initialPersons="0" loadedPersons="0" unloadedPersons="0" initialContainers="0" loadedContainers="0" unloadedContainers="0" busStop="410459657"/>
    <stopinfo id="3_bus_43:1" type="bus" lane="445716787_0" pos="38.91" parking="0" started="330.00" ended="360.00" delay="-1.00" initialPersons="0" loadedPersons="0" unloadedPersons="0" initialContainers="0" loadedContainers="0" unloadedContainers="0" busStop="410481986"/>
    <stopinfo id="1_bus_43:0" type="bus" lane="349416402_0" pos="140.86" parking="0" started="332.00" ended="362.00" delay="-1.00" initialPersons="0" loadedPersons="0" unloadedPersons="0" initialContainers="0" loadedContainers="0" unloadedContainers="0" busStop="8926967788"/>
    <stopinfo id="3_bus_43:1" type="bus" lane="445716787_0" pos="40.03" parking="0" started="361.00" ended="391.00" delay="-1.00" initialPersons="0" loadedPersons="0" unloadedPersons="0" initialContainers="0" loadedContainers="0" unloadedContainers="0" busStop="410481966"/>
    <stopinfo id="0_bus_22:0" type="bus" lane="630160531_0" pos="31.15" parking="0" started="393.00" ended="423.00" delay="-1.00" initialPersons="0" loadedPersons="0" unloadedPersons="0" initialContainers="0" loadedContainers="0" unloadedContainers="0" busStop="410459651"/>
    <stopinfo id="1_bus_43:0" type="bus" lane="717470516_0" pos="47.21" parking="0" started="395.00" ended="425.00" delay="-1.00" initialPersons="0" loadedPersons="0" unloadedPersons="0" initialContainers="0" loadedContainers="0" unloadedContainers="0" busStop="410474760"/>
    <stopinfo id="1_bus_43:0" type="bus" lane="445716748_0" pos="41.58" parking="0" started="449.00" ended="479.00" delay="-1.00" initialPersons="0" loadedPersons="0" unloadedPersons="0" initialContainers="0" loadedContainers="0" unloadedContainers="0" busStop="410474348"/>
    <stopinfo id="0_bus_22:0" type="bus" lane="630163199_0" pos="23.99" parking="0" started="481.00" ended="511.00" delay="-1.00" initialPersons="0" loadedPersons="0" unloadedPersons="0" initialContainers="0" loadedContainers="0" unloadedContainers="0" busStop="410467153"/>
    <stopinfo id="3_bus_43:1" type="bus" lane="478162426_0" pos="81.73" parking="0" started="507.00" ended="537.00" delay="-1.00" initialPersons="0" loadedPersons="0" unloadedPersons="0" initialContainers="0" loadedContainers="0" unloadedContainers="0" busStop="410461660"/>
    <stopinfo id="1_bus_43:0" type="bus" lane="22652564_0" pos="10.30" parking="0" started="536.00" ended="566.00" delay="-1.00" initialPersons="0" loadedPersons="0" unloadedPersons="0" initialContainers="0" loadedContainers="0" unloadedContainers="0" busStop="1849631269"/>
    <stopinfo id="0_bus_22:0" type="bus" lane="661628136_0" pos="27.43" parking="0" started="555.00" ended="585.00" delay="-1.00" initialPersons="0" loadedPersons="0" unloadedPersons="0" initialContainers="0" loadedContainers="0" unloadedContainers="0" busStop="410462101"/>
    <stopinfo id="3_bus_43:1" type="bus" lane="538417615#0_0" pos="15.72" parking="0" started="559.00" ended="589.00" delay="-1.00" initialPersons="0" loadedPersons="0" unloadedPersons="0" initialContainers="0" loadedContainers="0" unloadedContainers="0" busStop="410467577"/>
    <stopinfo id="0_bus_22:0" type="bus" lane="661628136_0" pos="28.31" parking="0" started="586.00" ended="616.00" delay="-1.00" initialPersons="0" loadedPersons="0" unloadedPersons="0" initialContainers="0" loadedContainers="0" unloadedContainers="0" busStop="410462103"/>
    <stopinfo id="1_bus_43:0" type="bus" lane="623715810#0_0" pos="7.70" parking="0" started="595.00" ended="625.00" delay="-1.00" initialPersons="0" loadedPersons="0" unloadedPersons="0" initialContainers="0" loadedContainers="0" unloadedContainers="0" busStop="2429952037"/>
    <stopinfo id="3_bus_43:1" type="bus" lane="22698750_0" pos="9.57" parking="0" started="614.00" ended="644.00" delay="-1.00" initialPersons="0" loadedPersons="0" unloadedPersons="0" initialContainers="0" loadedContainers="0" unloadedContainers="0" busStop="410467572"/>
    <stopinfo id="3_bus_43:1" type="bus" lane="22698750_0" pos="10.60" parking="0" started="645.00" ended="675.00" delay="-1.00" initialPersons="0" loadedPersons="0" unloadedPersons="0" initialContainers="0" loadedContainers="0" unloadedContainers="0" busStop="410467565"/>
    <stopinfo id="1_bus_43:0" type="bus" lane="632378379#0_0" pos="11.65" parking="0" started="695.00" ended="725.00" delay="-1.00" initialPersons="0" loadedPersons="0" unloadedPersons="0" initialContainers="0" loadedContainers="0" unloadedContainers="0" busStop="1849631273"/>
    <stopinfo id="0_bus_22:0" type="bus" lane="632203646_0" pos="100.99" parking="0" started="710.00" ended="740.00" delay="-1.00" initialPersons="0" loadedPersons="0" unloadedPersons="0" initialContainers="0" loadedContainers="0" unloadedContainers="0" busStop="410475114"/>
    <stopinfo id="3_bus_43:1" type="bus" lane="661351281_0" pos="67.58" parking="0" started="740.00" ended="770.00" delay="-1.00" initialPersons="0" loadedPersons="0" unloadedPersons="0" initialContainers="0" loadedContainers="0" unloadedContainers="0" busStop="410467569"/>
    <stopinfo id="0_bus_22:0" type="bus" lane="479079789_0" pos="36.62" parking="0" started="773.00" ended="803.00" delay="-1.00" initialPersons="0" loadedPersons="0" unloadedPersons="0" initialContainers="0" loadedContainers="0" unloadedContainers="0" busStop="1531005322"/>
    <stopinfo id="1_bus_43:0" type="bus" lane="445716683_0" pos="66.19" parking="0" started="776.00" ended="806.00" delay="-1.00" initialPersons="0" loadedPersons="0" unloadedPersons="0" initialContainers="0" loadedContainers="0" unloadedContainers="0" busStop="410462266"/>
    <stopinfo id="3_bus_43:1" type="bus" lane="661351279_0" pos="20.50" parking="0" started="805.00" ended="835.00" delay="-1.00" initialPersons="0" loadedPersons="0" unloadedPersons="0" initialContainers="0" loadedContainers="0" unloadedContainers="0" busStop="410467570"/>
    <stopinfo id="1_bus_43:0" type="bus" lane="476703994_0" pos="26.47" parking="0" started="822.00" ended="852.00" delay="-1.00" initialPersons="0" loadedPersons="0" unloadedPersons="0" initialContainers="0" loadedContainers="0" unloadedContainers="0" busStop="410462293"/>
    <stopinfo id="0_bus_22:0" type="bus" lane="22293549_0" pos="181.32" parking="0" started="834.00" ended="864.00" delay="-1.00" initialPersons="0" loadedPersons="0" unloadedPersons="0" initialContainers="0" loadedContainers="0" unloadedContainers="0" busStop="410483103"/>
    <stopinfo id="3_bus_43:1" type="bus" lane="131891598_0" pos="67.99" parking="0" started="876.00" ended="906.00" delay="-1.00" initialPersons="0" loadedPersons="0" unloadedPersons="0" initialContainers="0" loadedContainers="0" unloadedContainers="0" busStop="410467563"/>
    <stopinfo id="1_bus_43:0" type="bus" lane="512918179_0" pos="34.62" parking="0" started="890.00" ended="920.00" delay="-1.00" initialPersons="0" loadedPersons="0" unloadedPersons="0" initialContainers="0" loadedContainers="0" unloadedContainers="0" busStop="410462211"/>
    <stopinfo id="0_bus_22:0" type="bus" lane="33264691#0_0" pos="18.83" parking="0" started="892.00" ended="922.00" delay="-1.00" initialPersons="0" loadedPersons="0" unloadedPersons="0" initialContainers="0" loadedContainers="0" unloadedContainers="0" busStop="410482520"/>
    <stopinfo id="3_bus_43:1" type="bus" lane="131891598_0" pos="167.12" parking="0" started="923.00" ended="953.00" delay="-1.00" initialPersons="0" loadedPersons="0" unloadedPersons="0" initialContainers="0" loadedContainers="0" unloadedContainers="0" busStop="410467568"/>
    <stopinfo id="1_bus_43:0" type="bus" lane="512918201#0_0" pos="11.16" parking="0" started="951.00" ended="981.00" delay="-1.00" initialPersons="0" loadedPersons="0" unloadedPersons="0" initialContainers="0" loadedContainers="0" unloadedContainers="0" busStop="410462291"/>
    <stopinfo id="0_bus_22:0" type="bus" lane="633299924_0" pos="36.75" parking="0" started="968.00" ended="998.00" delay="-1.00" initialPersons="0" loadedPersons="0" unloadedPersons="0" initialContainers="0" loadedContainers="0" unloadedContainers="0" busStop="410482572"/>
    <stopinfo id="3_bus_43:1" type="bus" lane="74527426_0" pos="15.15" parking="0" started="1007.00" ended="1037.00" delay="-1.00" initialPersons="0" loadedPersons="0" unloadedPersons="0" initialContainers="0" loadedContainers="0" unloadedContainers="0" busStop="410467552"/>
    <stopinfo id="0_bus_22:0" type="bus" lane="474929430_0" pos="19.15" parking="0" started="1022.00" ended="1052.00" delay="-1.00" initialPersons="0" loadedPersons="0" unloadedPersons="0" initialContainers="0" loadedContainers="0" unloadedContainers="0" busStop="410482568"/>
    <stopinfo id="1_bus_43:0" type="bus" lane="74668469_0" pos="210.32" parking="0" started="1040.00" ended="1070.00" delay="-1.00" initialPersons="0" loadedPersons="0" unloadedPersons="0" initialContainers="0" loadedContainers="0" unloadedContainers="0" busStop="410486991"/>
    <stopinfo id="3_bus_43:1" type="bus" lane="22698333_0" pos="129.91" parking="0" started="1068.00" ended="1098.00" delay="-1.00" initialPersons="0" loadedPersons="0" unloadedPersons="0" initialContainers="0" loadedContainers="0" unloadedContainers="0" busStop="410467573"/>
    <stopinfo id="0_bus_22:0" type="bus" lane="631844130_0" pos="88.08" parking="0" started="1093.00" ended="1123.00" delay="-1.00" initialPersons="0" loadedPersons="0" unloadedPersons="0" initialContainers="0" loadedContainers="0" unloadedContainers="0" busStop="410482491"/>
    <stopinfo id="1_bus_43:0" type="bus" lane="74869296_0" pos="65.88" parking="0" started="1112.00" ended="1142.00" delay="-1.00" initialPersons="0" loadedPersons="0" unloadedPersons="0" initialContainers="0" loadedContainers="0" unloadedContainers="0" busStop="410486955"/>
    <stopinfo id="3_bus_43:1" type="bus" lane="585646223#0_0" pos="17.96" parking="0" started="1125.00" ended="1155.00" delay="-1.00" initialPersons="0" loadedPersons="0" unloadedPersons="0" initialContainers="0" loadedContainers="0" unloadedContainers="0" busStop="410467559"/>
    <stopinfo id="0_bus_22:0" type="bus" lane="631844130_0" pos="164.79" parking="0" started="1139.00" ended="1169.00" delay="-1.00" initialPersons="0" loadedPersons="0" unloadedPersons="0" initialContainers="0" loadedContainers="0" unloadedContainers="0" busStop="410482562"/>
    <stopinfo id="1_bus_43:0" type="bus" lane="34905413_0" pos="34.59" parking="0" started="1179.00" ended="1209.00" delay="-1.00" initialPersons="0" loadedPersons="0" unloadedPersons="0" initialContainers="0" loadedContainers="0" unloadedContainers="0" busStop="4430976208"/>
    <stopinfo id="0_bus_22:0" type="bus" lane="500368905_0" pos="103.67" parking="0" started="1220.00" ended="1250.00" delay="-1.00" initialPersons="0" loadedPersons="0" unloadedPersons="0" initialContainers="0" loadedContainers="0" unloadedContainers="0" busStop="410482564"/>
    <stopinfo id="3_bus_43:1" type="bus" lane="45065755_0" pos="111.05" parking="0" started="1222.00" ended="1252.00" delay="-1.00" initialPersons="0" loadedPersons="0" unloadedPersons="0" initialContainers="0" loadedContainers="0" unloadedContainers="0" busStop="410459493"/>
    <stopinfo id="1_bus_43:0" type="bus" lane="633197069_0" pos="16.10" parking="0" started="1238.00" ended="1268.00" delay="-1.00" initialPersons="0" loadedPersons="0" unloadedPersons="0" initialContainers="0" loadedContainers="0" unloadedContainers="0" busStop="410486969"/>
    <stopinfo id="0_bus_22:0" type="bus" lane="661665982_0" pos="107.56" parking="0" started="1281.00" ended="1311.00" delay="-1.00" initialPersons="0" loadedPersons="0" unloadedPersons="0" initialContainers="0" loadedContainers="0" unloadedContainers="0" busStop="410482570"/>
    <stopinfo id="1_bus_43:0" type="bus" lane="175959568_0" pos="45.59" parking="0" started="1309.00" ended="1339.00" delay="-1.00" initialPersons="0" loadedPersons="0" unloadedPersons="0" initialContainers="0" loadedContainers="0" unloadedContainers="0" busStop="1855320978"/>
    <stopinfo id="3_bus_43:1" type="bus" lane="651916279_0" pos="38.08" parking="0" started="1322.00" ended="1352.00" delay="-1.00" initialPersons="0" loadedPersons="0" unloadedPersons="0" initialContainers="0" loadedContainers="0" unloadedContainers="0" busStop="410478270"/>
    <stopinfo id="0_bus_22:0" type="bus" lane="661665982_0" pos="263.31" parking="0" started="1333.00" ended="1363.00" delay="-1.00" initialPersons="0" loadedPersons="0" unloadedPersons="0" initialContainers="0" loadedContainers="0" unloadedContainers="0" busStop="410482551"/>
    <stopinfo id="1_bus_43:0" type="bus" lane="630829769_0" pos="73.29" parking="0" started="1363.00" ended="1393.00" delay="-1.00" initialPersons="0" loadedPersons="0" unloadedPersons="0" initialContainers="0" loadedContainers="0" unloadedContainers="0" busStop="410486966"/>
    <stopinfo id="1_bus_43:0" type="bus" lane="630829769_0" pos="73.93" parking="0" started="1394.00" ended="1424.00" delay="-1.00" initialPersons="0" loadedPersons="0" unloadedPersons="0" initialContainers="0" loadedContainers="0" unloadedContainers="0" busStop="410486516"/>
    <stopinfo id="3_bus_43:1" type="bus" lane="536913690_0" pos="108.86" parking="0" started="1396.00" ended="1426.00" delay="-1.00" initialPersons="0" loadedPersons="0" unloadedPersons="0" initialContainers="0" loadedContainers="0" unloadedContainers="0" busStop="1849457004"/>
    <stopinfo id="0_bus_22:0" type="bus" lane="630419696#0_0" pos="12.11" parking="0" started="1397.00" ended="1427.00" delay="-1.00" initialPersons="0" loadedPersons="0" unloadedPersons="0" initialContainers="0" loadedContainers="0" unloadedContainers="0" busStop="410471081"/>
    <stopinfo id="0_bus_22:0" type="bus" lane="639549066_0" pos="34.17" parking="0" started="1464.00" ended="1494.00" delay="-1.00" initialPersons="0" loadedPersons="0" unloadedPersons="0" initialContainers="0" loadedContainers="0" unloadedContainers="0" busStop="410471030"/>
    <stopinfo id="1_bus_43:0" type="bus" lane="475163615_0" pos="31.74" parking="0" started="1470.00" ended="1500.00" delay="-1.00" initialPersons="0" loadedPersons="0" unloadedPersons="0" initialContainers="0" loadedContainers="0" unloadedContainers="0" busStop="410486293"/>
    <stopinfo id="3_bus_43:1" type="bus" lane="536913672_0" pos="29.79" parking="0" started="1475.00" ended="1505.00" delay="-1.00" initialPersons="0" loadedPersons="0" unloadedPersons="0" initialContainers="0" loadedContainers="0" unloadedContainers="0" busStop="410478269"/>
    <stopinfo id="3_bus_43:1" type="bus" lane="536913672_0" pos="30.48" parking="0" started="1506.00" ended="1536.00" delay="-1.00" initialPersons="0" loadedPersons="0" unloadedPersons="0" initialContainers="0" loadedContainers="0" unloadedContainers="0" busStop="410478280"/>
    <stopinfo id="0_bus_22:0" type="bus" lane="639916002_0" pos="25.95" parking="0" started="1546.00" ended="1576.00" delay="-1.00" initialPersons="0" loadedPersons="0" unloadedPersons="0" initialContainers="0" loadedContainers="0" unloadedContainers="0" busStop="410480716"/>
    <stopinfo id="1_bus_43:0" type="bus" lane="632203646_0" pos="100.99" parking="0" started="1557.00" ended="1587.00" delay="-1.00" initialPersons="0" loadedPersons="0" unloadedPersons="0" initialContainers="0" loadedContainers="0" unloadedContainers="0" busStop="410475114"/>
    <stopinfo id="0_bus_22:0" type="bus" lane="74746296_0" pos="200.17" parking="0" started="1609.00" ended="1639.00" delay="-1.00" initialPersons="0" loadedPersons="0" unloadedPersons="0" initialContainers="0" loadedContainers="0" unloadedContainers="0" busStop="410480722"/>
    <stopinfo id="1_bus_43:0" type="bus" lane="479079789_0" pos="36.64" parking="0" started="1618.00" ended="1648.00" delay="-1.00" initialPersons="0" loadedPersons="0" unloadedPersons="0" initialContainers="0" loadedContainers="0" unloadedContainers="0" busStop="1531005322"/>
    <stopinfo id="3_bus_43:1" type="bus" lane="747402010_0" pos="27.85" parking="0" started="1620.00" ended="1650.00" delay="-1.00" initialPersons="0" loadedPersons="0" unloadedPersons="0" initialContainers="0" loadedContainers="0" unloadedContainers="0" busStop="1849631261"/>
    <stopinfo id="0_bus_22:0" type="bus" lane="74746296_0" pos="328.24" parking="0" started="1658.00" ended="1688.00" delay="-1.00" initialPersons="0" loadedPersons="0" unloadedPersons="0" initialContainers="0" loadedContainers="0" unloadedContainers="0" busStop="410480721"/>
    <stopinfo id="3_bus_43:1" type="bus" lane="585646214_0" pos="33.83" parking="0" started="1667.00" ended="1697.00" delay="-1.00" initialPersons="0" loadedPersons="0" unloadedPersons="0" initialContainers="0" loadedContainers="0" unloadedContainers="0" busStop="410470849"/>
    <stopinfo id="1_bus_43:0" type="bus" lane="22293549_0" pos="181.36" parking="0" started="1680.00" ended="1710.00" delay="-1.00" initialPersons="0" loadedPersons="0" unloadedPersons="0" initialContainers="0" loadedContainers="0" unloadedContainers="0" busStop="410483103"/>
    <stopinfo id="0_bus_22:0" type="bus" lane="477574135_0" pos="141.89" parking="0" started="1728.00" ended="1758.00" delay="-1.00" initialPersons="0" loadedPersons="0" unloadedPersons="0" initialContainers="0" loadedContainers="0" unloadedContainers="0" busStop="5701793241"/>
    <stopinfo id="3_bus_43:1" type="bus" lane="585646212#0_0" pos="15.41" parking="0" started="1729.00" ended="1759.00" delay="-1.00" initialPersons="0" loadedPersons="0" unloadedPersons="0" initialContainers="0" loadedContainers="0" unloadedContainers="0" busStop="410470932"/>
    <stopinfo id="1_bus_43:0" type="bus" lane="33264691#0_0" pos="18.84" parking="0" started="1738.00" ended="1768.00" delay="-1.00" initialPersons="0" loadedPersons="0" unloadedPersons="0" initialContainers="0" loadedContainers="0" unloadedContainers="0" busStop="410482520"/>
    <stopinfo id="0_bus_22:0" type="bus" lane="636737164_0" pos="42.15" parking="0" started="1778.00" ended="1808.00" delay="-1.00" initialPersons="0" loadedPersons="0" unloadedPersons="0" initialContainers="0" loadedContainers="0" unloadedContainers="0" busStop="410480724"/>
    <stopinfo id="3_bus_43:1" type="bus" lane="33793689_0" pos="20.50" parking="0" started="1794.00" ended="1824.00" delay="-1.00" initialPersons="0" loadedPersons="0" unloadedPersons="0" initialContainers="0" loadedContainers="0" unloadedContainers="0" busStop="410470905"/>
    <stopinfo id="1_bus_43:0" type="bus" lane="633299924_0" pos="36.76" parking="0" started="1814.00" ended="1844.00" delay="-1.00" initialPersons="0" loadedPersons="0" unloadedPersons="0" initialContainers="0" loadedContainers="0" unloadedContainers="0" busStop="410482572"/>
    <stopinfo id="0_bus_22:0" type="bus" lane="447712957_0" pos="39.64" parking="0" started="1843.00" ended="1873.00" delay="-1.00" initialPersons="0" loadedPersons="0" unloadedPersons="0" initialContainers="0" loadedContainers="0" unloadedContainers="0" busStop="410464248"/>
    <stopinfo id="2_bus_22:1" type="bus" lane="632562097#0_0" pos="7.70" parking="0" started="1854.00" ended="1884.00" delay="-1.00" initialPersons="0" loadedPersons="0" unloadedPersons="0" initialContainers="0" loadedContainers="0" unloadedContainers="0" busStop="410464251"/>
    <stopinfo id="1_bus_43:0" type="bus" lane="474929430_0" pos="19.16" parking="0" started="1868.00" ended="1898.00" delay="-1.00" initialPersons="0" loadedPersons="0" unloadedPersons="0" initialContainers="0" loadedContainers="0" unloadedContainers="0" busStop="410482568"/>
    <stopinfo id="2_bus_22:1" type="bus" lane="655145244_0" pos="59.68" parking="0" started="1909.00" ended="1939.00" delay="-1.00" initialPersons="0" loadedPersons="0" unloadedPersons="0" initialContainers="0" loadedContainers="0" unloadedContainers="0" busStop="1995038394"/>
    <stopinfo id="0_bus_22:0" type="bus" lane="587048092_0" pos="44.40" parking="0" started="1912.00" ended="1942.00" delay="-1.00" initialPersons="0" loadedPersons="0" unloadedPersons="0" initialContainers="0" loadedContainers="0" unloadedContainers="0" busStop="410465916"/>
    <stopinfo id="3_bus_43:1" type="bus" lane="587050475#0_0" pos="11.11" parking="0" started="1913.00" ended="1943.00" delay="-1.00" initialPersons="0" loadedPersons="0" unloadedPersons="0" initialContainers="0" loadedContainers="0" unloadedContainers="0" busStop="410470989"/>
    <stopinfo id="1_bus_43:0" type="bus" lane="631844130_0" pos="88.09" parking="0" started="1938.00" ended="1968.00" delay="-1.00" initialPersons="0" loadedPersons="0" unloadedPersons="0" initialContainers="0" loadedContainers="0" unloadedContainers="0" busStop="410482491"/>
    <stopinfo id="2_bus_22:1" type="bus" lane="770367113_0" pos="49.63" parking="0" started="1974.00" ended="2004.00" delay="-1.00" initialPersons="0" loadedPersons="0" unloadedPersons="0" initialContainers="0" loadedContainers="0" unloadedContainers="0" busStop="410465918"/>
    <stopinfo id="0_bus_22:0" type="bus" lane="74553776_0" pos="37.69" parking="0" started="1979.00" ended="2009.00" delay="-1.00" initialPersons="0" loadedPersons="0" unloadedPersons="0" initialContainers="0" loadedContainers="0" unloadedContainers="0" busStop="410465917"/>
    <stopinfo id="1_bus_43:0" type="bus" lane="631844130_0" pos="164.79" parking="0" started="1984.00" ended="2014.00" delay="-1.00" initialPersons="0" loadedPersons="0" unloadedPersons="0" initialContainers="0" loadedContainers="0" unloadedContainers="0" busStop="410482562"/>
    <stopinfo id="3_bus_43:1" type="bus" lane="639549065_0" pos="63.89" parking="0" started="1988.00" ended="2018.00" delay="-1.00" initialPersons="0" loadedPersons="0" unloadedPersons="0" initialContainers="0" loadedContainers="0" unloadedContainers="0" busStop="410470884"/>
    <stopinfo id="2_bus_22:1" type="bus" lane="655147259_0" pos="70.00" parking="0" started="2032.00" ended="2062.00" delay="-1.00" initialPersons="0" loadedPersons="0" unloadedPersons="0" initialContainers="0" loadedContainers="0" unloadedContainers="0" busStop="410465914"/>
    <stopinfo id="0_bus_22:0" type="bus" lane="473440854_0" pos="11.71" parking="0" started="2050.00" ended="2080.00" delay="-1.00" initialPersons="0" loadedPersons="0" unloadedPersons="0" initialContainers="0" loadedContainers="0" unloadedContainers="0" busStop="410465915"/>
    <stopinfo id="1_bus_43:0" type="bus" lane="500368905_0" pos="103.66" parking="0" started="2066.00" ended="2096.00" delay="-1.00" initialPersons="0" loadedPersons="0" unloadedPersons="0" initialContainers="0" loadedContainers="0" unloadedContainers="0" busStop="410482564"/>
    <stopinfo id="3_bus_43:1" type="bus" lane="655041207_0" pos="86.22" parking="0" started="2067.00" ended="2097.00" delay="-1.00" initialPersons="0" loadedPersons="0" unloadedPersons="0" initialContainers="0" loadedContainers="0" unloadedContainers="0" busStop="410482569"/>
    <stopinfo id="0_bus_22:0" type="bus" lane="585646221#0_0" pos="12.26" parking="0" started="2123.00" ended="2153.00" delay="-1.00" initialPersons="0" loadedPersons="0" unloadedPersons="0" initialContainers="0" loadedContainers="0" unloadedContainers="0" busStop="410462762"/>
    <stopinfo id="1_bus_43:0" type="bus" lane="661665982_0" pos="107.55" parking="0" started="2126.00" ended="2156.00" delay="-1.00" initialPersons="0" loadedPersons="0" unloadedPersons="0" initialContainers="0" loadedContainers="0" unloadedContainers="0" busStop="410482570"/>
    <stopinfo id="3_bus_43:1" type="bus" lane="33264605_0" pos="15.90" parking="0" started="2133.00" ended="2163.00" delay="-1.00" initialPersons="0" loadedPersons="0" unloadedPersons="0" initialContainers="0" loadedContainers="0" unloadedContainers="0" busStop="410482563"/>
    <stopinfo id="3_bus_43:1" type="bus" lane="633245786_0" pos="33.72" parking="0" started="2177.00" ended="2207.00" delay="-1.00" initialPersons="0" loadedPersons="0" unloadedPersons="0" initialContainers="0" loadedContainers="0" unloadedContainers="0" busStop="410482567"/>
    <stopinfo id="1_bus_43:0" type="bus" lane="661665982_0" pos="263.31" parking="0" started="2177.00" ended="2207.00" delay="-1.00" initialPersons="0" loadedPersons="0" unloadedPersons="0" initialContainers="0" loadedContainers="0" unloadedContainers="0" busStop="410482551"/>
    <stopinfo id="0_bus_22:0" type="bus" lane="23816952_0" pos="85.49" parking="0" started="2222.00" ended="2252.00" delay="-1.00" initialPersons="0" loadedPersons="0" unloadedPersons="0" initialContainers="0" loadedContainers="0" unloadedContainers="0" busStop="410466111"/>
    <stopinfo id="1_bus_43:0" type="bus" lane="630419696#0_0" pos="12.09" parking="0" started="2240.00" ended="2270.00" delay="-1.00" initialPersons="0" loadedPersons="0" unloadedPersons="0" initialContainers="0" loadedContainers="0" unloadedContainers="0" busStop="410471081"/>
    <stopinfo id="3_bus_43:1" type="bus" lane="358645124_0" pos="8.43" parking="0" started="2260.00" ended="2290.00" delay="-1.00" initialPersons="0" loadedPersons="0" unloadedPersons="0" initialContainers="0" loadedContainers="0" unloadedContainers="0" busStop="410482565"/>
    <stopinfo id="1_bus_43:0" type="bus" lane="639549066_0" pos="34.18" parking="0" started="2306.00" ended="2336.00" delay="-1.00" initialPersons="0" loadedPersons="0" unloadedPersons="0" initialContainers="0" loadedContainers="0" unloadedContainers="0" busStop="410471030"/>
    <stopinfo id="3_bus_43:1" type="bus" lane="358645124_0" pos="206.36" parking="0" started="2313.00" ended="2343.00" delay="-1.00" initialPersons="0" loadedPersons="0" unloadedPersons="0" initialContainers="0" loadedContainers="0" unloadedContainers="0" busStop="3865151080"/>
    <stopinfo id="3_bus_43:1" type="bus" lane="476380447_0" pos="49.36" parking="0" started="2362.00" ended="2392.00" delay="-1.00" initialPersons="0" loadedPersons="0" unloadedPersons="0" initialContainers="0" loadedContainers="0" unloadedContainers="0" busStop="1847940083"/>
    <stopinfo id="3_bus_43:1" type="bus" lane="539379658_0" pos="7.70" parking="0" started="2427.00" ended="2457.00" delay="-1.00" initialPersons="0" loadedPersons="0" unloadedPersons="0" initialContainers="0" loadedContainers="0" unloadedContainers="0" busStop="410482566"/>
    <stopinfo id="1_bus_43:0" type="bus" lane="587050477#0_0" pos="7.70" parking="0" started="2440.00" ended="2470.00" delay="-1.00" initialPersons="0" loadedPersons="0" unloadedPersons="0" initialContainers="0" loadedContainers="0" unloadedContainers="0" busStop="410470959"/>
    <stopinfo id="3_bus_43:1" type="bus" lane="74769762_0" pos="86.17" parking="0" started="2501.00" ended="2531.00" delay="-1.00" initialPersons="0" loadedPersons="0" unloadedPersons="0" initialContainers="0" loadedContainers="0" unloadedContainers="0" busStop="410482462"/>
    <stopinfo id="1_bus_43:0" type="bus" lane="585706001_0" pos="93.52" parking="0" started="2513.00" ended="2543.00" delay="-1.00" initialPersons="0" loadedPersons="0" unloadedPersons="0" initialContainers="0" loadedContainers="0" unloadedContainers="0" busStop="410471005"/>
    <stopinfo id="3_bus_43:1" type="bus" lane="74553749_0" pos="61.34" parking="0" started="2565.00" ended="2595.00" delay="-1.00" initialPersons="0" loadedPersons="0" unloadedPersons="0" initialContainers="0" loadedContainers="0" unloadedContainers="0" busStop="410483065"/>
    <stopinfo id="1_bus_43:0" type="bus" lane="585646209#0_0" pos="9.25" parking="0" started="2569.00" ended="2599.00" delay="-1.00" initialPersons="0" loadedPersons="0" unloadedPersons="0" initialContainers="0" loadedContainers="0" unloadedContainers="0" busStop="410464255"/>
    <stopinfo id="3_bus_43:1" type="bus" lane="633397743_0" pos="24.88" parking="0" started="2632.00" ended="2662.00" delay="-1.00" initialPersons="0" loadedPersons="0" unloadedPersons="0" initialContainers="0" loadedContainers="0" unloadedContainers="0" busStop="410475111"/>
    <stopinfo id="1_bus_43:0" type="bus" lane="652012496_0" pos="45.47" parking="0" started="2655.00" ended="2685.00" delay="-1.00" initialPersons="0" loadedPersons="0" unloadedPersons="0" initialContainers="0" loadedContainers="0" unloadedContainers="0" busStop="410478275"/>
    <stopinfo id="3_bus_43:1" type="bus" lane="633397743_0" pos="26.05" parking="0" started="2663.00" ended="2693.00" delay="-1.00" initialPersons="0" loadedPersons="0" unloadedPersons="0" initialContainers="0" loadedContainers="0" unloadedContainers="0" busStop="410475115"/>
    <stopinfo id="1_bus_43:0" type="bus" lane="-22810638_0" pos="26.15" parking="0" started="2724.00" ended="2754.00" delay="-1.00" initialPersons="0" loadedPersons="0" unloadedPersons="0" initialContainers="0" loadedContainers="0" unloadedContainers="0" busStop="-410478274"/>
    <stopinfo id="3_bus_43:1" type="bus" lane="448937648_0" pos="56.44" parking="0" started="2751.00" ended="2781.00" delay="-1.00" initialPersons="0" loadedPersons="0" unloadedPersons="0" initialContainers="0" loadedContainers="0" unloadedContainers="0" busStop="410486292"/>
    <stopinfo id="1_bus_43:0" type="bus" lane="-22810638_0" pos="72.27" parking="0" started="2766.00" ended="2796.00" delay="-1.00" initialPersons="0" loadedPersons="0" unloadedPersons="0" initialContainers="0" loadedContainers="0" unloadedContainers="0" busStop="-410478273"/>
    <stopinfo id="3_bus_43:1" type="bus" lane="174765849_0" pos="45.64" parking="0" started="2810.00" ended="2840.00" delay="-1.00" initialPersons="0" loadedPersons="0" unloadedPersons="0" initialContainers="0" loadedContainers="0" unloadedContainers="0" busStop="1854311858"/>
    <stopinfo id="1_bus_43:0" type="bus" lane="-747299409_0" pos="24.50" parking="0" started="2843.00" ended="2873.00" delay="-1.00" initialPersons="0" loadedPersons="0" unloadedPersons="0" initialContainers="0" loadedContainers="0" unloadedContainers="0" busStop="-1849457018"/>
    <stopinfo id="3_bus_43:1" type="bus" lane="633146417_0" pos="58.00" parking="0" started="2891.00" ended="2921.00" delay="-1.00" initialPersons="0" loadedPersons="0" unloadedPersons="0" initialContainers="0" loadedContainers="0" unloadedContainers="0" busStop="410486964"/>
    <stopinfo id="1_bus_43:0" type="bus" lane="536913703_0" pos="7.68" parking="0" started="2914.00" ended="2944.00" delay="-1.00" initialPersons="0" loadedPersons="0" unloadedPersons="0" initialContainers="0" loadedContainers="0" unloadedContainers="0" busStop="410478271"/>
    <stopinfo id="3_bus_43:1" type="bus" lane="633146417_0" pos="164.86" parking="0" started="2938.00" ended="2968.00" delay="-1.00" initialPersons="0" loadedPersons="0" unloadedPersons="0" initialContainers="0" loadedContainers="0" unloadedContainers="0" busStop="410486828"/>
    <stopinfo id="3_bus_43:1" type="bus" lane="537579061_0" pos="26.43" parking="0" started="3003.00" ended="3033.00" delay="-1.00" initialPersons="0" loadedPersons="0" unloadedPersons="0" initialContainers="0" loadedContainers="0" unloadedContainers="0" busStop="410486963"/>
    <stopinfo id="1_bus_43:0" type="bus" lane="535665920_0" pos="13.94" parking="0" started="3020.00" ended="3050.00" delay="-1.00" initialPersons="0" loadedPersons="0" unloadedPersons="0" initialContainers="0" loadedContainers="0" unloadedContainers="0" busStop="410459494"/>
    <stopinfo id="3_bus_43:1" type="bus" lane="475171829_0" pos="64.21" parking="0" started="3074.00" ended="3104.00" delay="-1.00" initialPersons="0" loadedPersons="0" unloadedPersons="0" initialContainers="0" loadedContainers="0" unloadedContainers="0" busStop="410486295"/>
    <stopinfo id="1_bus_43:0" type="bus" lane="467731257#0_0" pos="64.55" parking="0" started="3117.00" ended="3147.00" delay="-1.00" initialPersons="0" loadedPersons="0" unloadedPersons="0" initialContainers="0" loadedContainers="0" unloadedContainers="0" busStop="4623289717"/>
    <stopinfo id="3_bus_43:1" type="bus" lane="630417422_0" pos="49.32" parking="0" started="3137.00" ended="3167.00" delay="-1.00" initialPersons="0" loadedPersons="0" unloadedPersons="0" initialContainers="0" loadedContainers="0" unloadedContainers="0" busStop="410486421"/>
    <stopinfo id="1_bus_43:0" type="bus" lane="474427034_0" pos="81.84" parking="0" started="3180.00" ended="3210.00" delay="-1.00" initialPersons="0" loadedPersons="0" unloadedPersons="0" initialContainers="0" loadedContainers="0" unloadedContainers="0" busStop="410467553"/>
    <stopinfo id="3_bus_43:1" type="bus" lane="445716684#0_0" pos="12.20" parking="0" started="3204.00" ended="3234.00" delay="-1.00" initialPersons="0" loadedPersons="0" unloadedPersons="0" initialContainers="0" loadedContainers="0" unloadedContainers="0" busStop="410462187"/>
    <stopinfo id="1_bus_43:0" type="bus" lane="22698751#0_0" pos="12.86" parking="0" started="3238.00" ended="3268.00" delay="-1.00" initialPersons="0" loadedPersons="0" unloadedPersons="0" initialContainers="0" loadedContainers="0" unloadedContainers="0" busStop="410467566"/>
    <stopinfo id="3_bus_43:1" type="bus" lane="512918195#0_0" pos="13.41" parking="0" started="3280.00" ended="3310.00" delay="-1.00" initialPersons="0" loadedPersons="0" unloadedPersons="0" initialContainers="0" loadedContainers="0" unloadedContainers="0" busStop="410462238"/>
    <stopinfo id="1_bus_43:0" type="bus" lane="74518787_0" pos="69.90" parking="0" started="3308.00" ended="3338.00" delay="-1.00" initialPersons="0" loadedPersons="0" unloadedPersons="0" initialContainers="0" loadedContainers="0" unloadedContainers="0" busStop="410467564"/>
    <stopinfo id="1_bus_43:0" type="bus" lane="74518787_0" pos="70.58" parking="0" started="3339.00" ended="3369.00" delay="-1.00" initialPersons="0" loadedPersons="0" unloadedPersons="0" initialContainers="0" loadedContainers="0" unloadedContainers="0" busStop="1268343846"/>
    <stopinfo id="3_bus_43:1" type="bus" lane="512918181#0_0" pos="7.62" parking="0" started="3342.00" ended="3372.00" delay="-1.00" initialPersons="0" loadedPersons="0" unloadedPersons="0" initialContainers="0" loadedContainers="0" unloadedContainers="0" busStop="410462292"/>
    <stopinfo id="3_bus_43:1" type="bus" lane="175959440_0" pos="49.69" parking="0" started="3408.00" ended="3438.00" delay="-1.00" initialPersons="0" loadedPersons="0" unloadedPersons="0" initialContainers="0" loadedContainers="0" unloadedContainers="0" busStop="410462285"/>
    <stopinfo id="1_bus_43:0" type="bus" lane="474210631_0" pos="136.23" parking="0" started="3433.00" ended="3463.00" delay="-1.00" initialPersons="0" loadedPersons="0" unloadedPersons="0" initialContainers="0" loadedContainers="0" unloadedContainers="0" busStop="410467574"/>
    <stopinfo id="3_bus_43:1" type="bus" lane="445716678#0_0" pos="9.96" parking="0" started="3463.00" ended="3493.00" delay="-1.00" initialPersons="0" loadedPersons="0" unloadedPersons="0" initialContainers="0" loadedContainers="0" unloadedContainers="0" busStop="1849631298"/>
    <stopinfo id="1_bus_43:0" type="bus" lane="474210631_0" pos="459.58" parking="0" started="3496.00" ended="3526.00" delay="-1.00" initialPersons="0" loadedPersons="0" unloadedPersons="0" initialContainers="0" loadedContainers="0" unloadedContainers="0" busStop="410467562"/>
    <stopinfo id="3_bus_43:1" type="bus" lane="624291888#0_0" pos="7.80" parking="0" started="3549.00" ended="3579.00" delay="-1.00" initialPersons="0" loadedPersons="0" unloadedPersons="0" initialContainers="0" loadedContainers="0" unloadedContainers="0" busStop="1848076678"/>
    <stopinfo id="1_bus_43:0" type="bus" lane="474431399_0" pos="117.10" parking="0" started="3560.00" ended="3590.00" delay="-1.00" initialPersons="0" loadedPersons="0" unloadedPersons="0" initialContainers="0" loadedContainers="0" unloadedContainers="0" busStop="410467567"/>
    <stopinfo id="3_bus_43:1" type="bus" lane="74549015#0_0" pos="9.08" parking="0" started="3634.00" ended="3664.00" delay="-1.00" initialPersons="0" loadedPersons="0" unloadedPersons="0" initialContainers="0" loadedContainers="0" unloadedContainers="0" busStop="1849631267"/>
    <stopinfo id="1_bus_43:0" type="bus" lane="474446538_0" pos="55.80" parking="0" started="3647.00" ended="3677.00" delay="-1.00" initialPersons="0" loadedPersons="0" unloadedPersons="0" initialContainers="0" loadedContainers="0" unloadedContainers="0" busStop="410467571"/>
    <stopinfo id="1_bus_43:0" type="bus" lane="474446538_0" pos="62.16" parking="0" started="3681.00" ended="3711.00" delay="-1.00" initialPersons="0" loadedPersons="0" unloadedPersons="0" initialContainers="0" loadedContainers="0" unloadedContainers="0" busStop="410461658"/>
    <stopinfo id="3_bus_43:1" type="bus" lane="174886203_0" pos="93.81" parking="0" started="3732.00" ended="3762.00" delay="-1.00" initialPersons="0" loadedPersons="0" unloadedPersons="0" initialContainers="0" loadedContainers="0" unloadedContainers="0" busStop="410474384"/>
    <stopinfo id="1_bus_43:0" type="bus" lane="585984926_0" pos="32.35" parking="0" started="3752.00" ended="3782.00" delay="-1.00" initialPersons="0" loadedPersons="0" unloadedPersons="0" initialContainers="0" loadedContainers="0" unloadedContainers="0" busStop="410481810"/>
    <stopinfo id="1_bus_43:0" type="bus" lane="585984926_0" pos="33.34" parking="0" started="3783.00" ended="3813.00" delay="-1.00" initialPersons="0" loadedPersons="0" unloadedPersons="0" initialContainers="0" loadedContainers="0" unloadedContainers="0" busStop="410481815"/>
    <stopinfo id="3_bus_43:1" type="bus" lane="445716751_0" pos="39.51" parking="0" started="3784.00" ended="3814.00" delay="-1.00" initialPersons="0" loadedPersons="0" unloadedPersons="0" initialContainers="0" loadedContainers="0" unloadedContainers="0" busStop="410474619"/>
    <stopinfo id="1_bus_43:0" type="bus" lane="585984926_0" pos="34.42" parking="0" started="3814.00" ended="3844.00" delay="-1.00" initialPersons="0" loadedPersons="0" unloadedPersons="0" initialContainers="0" loadedContainers="0" unloadedContainers="0" busStop="410481781"/>
    <stopinfo id="1_bus_43:0" type="bus" lane="585984926_0" pos="35.23" parking="0" started="3845.00" ended="3875.00" delay="-1.00" initialPersons="0" loadedPersons="0" unloadedPersons="0" initialContainers="0" loadedContainers="0" unloadedContainers="0" busStop="410481783"/>
    <stopinfo id="3_bus_43:1" type="bus" lane="74957634_0" pos="45.13" parking="0" started="3846.00" ended="3876.00" delay="-1.00" initialPersons="0" loadedPersons="0" unloadedPersons="0" initialContainers="0" loadedContainers="0" unloadedContainers="0" busStop="8926967789"/>
    <stopinfo id="3_bus_43:1" type="bus" lane="391007733#0_0" pos="12.03" parking="0" started="3918.00" ended="3948.00" delay="-1.00" initialPersons="0" loadedPersons="0" unloadedPersons="0" initialContainers="0" loadedContainers="0" unloadedContainers="0" busStop="3737158812"/>
    <stopinfo id="3_bus_43:1" type="bus" lane="582412286#0_0" pos="10.75" parking="0" started="3980.00" ended="4010.00" delay="-1.00" initialPersons="0" loadedPersons="0" unloadedPersons="0" initialContainers="0" loadedContainers="0" unloadedContainers="0" busStop="1849631343"/>
    <stopinfo id="1_bus_43:0" type="bus" lane="585984913_0" pos="45.25" parking="0" started="3988.00" ended="4018.00" delay="-1.00" initialPersons="0" loadedPersons="0" unloadedPersons="0" initialContainers="0" loadedContainers="0" unloadedContainers="0" busStop="410482047"/>
    <stopinfo id="3_bus_43:1" type="bus" lane="33194100_0" pos="72.17" parking="0" started="4056.00" ended="4086.00" delay="-1.00" initialPersons="0" loadedPersons="0" unloadedPersons="0" initialContainers="0" loadedContainers="0" unloadedContainers="0" busStop="3865151068"/>
    <stopinfo id="1_bus_43:0" type="bus" lane="769243289_0" pos="26.08" parking="0" started="4078.00" ended="4108.00" delay="-1.00" initialPersons="0" loadedPersons="0" unloadedPersons="0" initialContainers="0" loadedContainers="0" unloadedContainers="0" busStop="410482019"/>
    <stopinfo id="1_bus_43:0" type="bus" lane="528461109_0" pos="16.46" parking="0" started="4147.00" ended="4177.00" delay="-1.00" initialPersons="0" loadedPersons="0" unloadedPersons="0" initialContainers="0" loadedContainers="0" unloadedContainers="0" busStop="1847713996"/>
    <stopinfo id="3_bus_43:1" type="bus" lane="631887962#0_0" pos="137.44" parking="0" started="4188.00" ended="4218.00" delay="-1.00" initialPersons="0" loadedPersons="0" unloadedPersons="0" initialContainers="0" loadedContainers="0" unloadedContainers="0" busStop="1847853709@6623041"/>
</stops>
